tests/__init__.py
tests/tests.py
trimkmeans/__init__.py
trimkmeans/metrics.py
trimkmeans/trimkmeans.py
trimkmeans-1.1.1.dist-info/LICENSE.txt
trimkmeans-1.1.1.dist-info/METADATA
trimkmeans-1.1.1.dist-info/WHEEL
trimkmeans-1.1.1.dist-info/top_level.txt
trimkmeans-1.1.1.dist-info/RECORD
