Metadata-Version: 2.1
Name: trimkmeans
Version: 1.1.1
Summary: The trimmed k-means clustering method
Home-page: https://github.com/ArthRie/trimkmeans
Author: Arthur Rieß
Author-email: a12035966@unet.univie.ac.at
Project-URL: Bug Tracker, https://github.com/ArthRie/trimkmeans/issues
Project-URL: repository, https://github.com/ArthRie/trimkmeans
Classifier: Programming Language :: Python :: 3
Classifier: License :: OSI Approved :: MIT License
Classifier: Operating System :: OS Independent
Requires-Python: >=3.6
License-File: LICENSE.txt
